ghidradbg/__init__.py
ghidradbg/arch.py
ghidradbg/commands.py
ghidradbg/hooks.py
ghidradbg/libraries.py
ghidradbg/methods.py
ghidradbg/py.typed
ghidradbg/schema.xml
ghidradbg/schema_exdi.xml
ghidradbg/util.py
ghidradbg/dbgmodel/DbgModel.idl
ghidradbg/dbgmodel/__init__.py
ghidradbg/dbgmodel/idatamodelmanager.py
ghidradbg/dbgmodel/idebughost.py
ghidradbg/dbgmodel/ihostdatamodelaccess.py
ghidradbg/dbgmodel/iiterableconcept.py
ghidradbg/dbgmodel/ikeyenumerator.py
ghidradbg/dbgmodel/imodeliterator.py
ghidradbg/dbgmodel/imodelmethod.py
ghidradbg/dbgmodel/imodelobject.py
ghidradbg/dbgmodel/irawenumerator.py
ghidradbg/dbgmodel/istringdisplayableconcept.py
ghidradbg/dbgmodel/tlb/dbgmodel.tlb
ghidradbg/exdi/exdi_commands.py
ghidradbg/exdi/exdi_methods.py
ghidradbg-12.0.dist-info/licenses/LICENSE
ghidradbg-12.0.dist-info/METADATA
ghidradbg-12.0.dist-info/WHEEL
ghidradbg-12.0.dist-info/top_level.txt
ghidradbg-12.0.dist-info/RECORD
